{"cameraMode":{"drawMode":0,"name":"Shaded","section":"Shading Mode"},"sceneLighting":true,"audioPlay":false,"sceneViewState":{"m_AlwaysRefresh":false,"showFog":true,"showSkybox":true,"showFlares":true,"showImageEffects":true,"showParticleSystems":true,"showVisualEffectGraphs":true,"m_FxEnabled":true},"in2DMode":false,"pivot":{"x":-0.6388422250747681,"y":9.051538467407227,"z":2.582592010498047},"rotation":{"x":0.171935573220253,"y":0.019201381132006646,"z":-0.0033784895204007627,"w":0.9850184917449951},"size":8.264116287231446,"orthographic":false}